qtrade/__init__.py
qtrade/_version.py
qtrade/questrade.py
qtrade/utility.py
qtrade-0.6.1.dist-info/LICENSE
qtrade-0.6.1.dist-info/METADATA
qtrade-0.6.1.dist-info/WHEEL
qtrade-0.6.1.dist-info/top_level.txt
qtrade-0.6.1.dist-info/RECORD
