Metadata-Version: 2.1
Name: qtrade
Version: 0.6.1
Summary: Questrade API wrapper for Python
Home-page: https://github.com/jborchma/qtrade
License: MIT
License-File: LICENSE
Requires-Dist: PyYAML >=5.1
Requires-Dist: requests >=2.14.2
